keyrunes_sdk/__init__.py
keyrunes_sdk/client.py
keyrunes_sdk/config.py
keyrunes_sdk/decorators.py
keyrunes_sdk/exceptions.py
keyrunes_sdk/models.py
keyrunes_python_sdk-0.1.0.dist-info/LICENSE
keyrunes_python_sdk-0.1.0.dist-info/METADATA
keyrunes_python_sdk-0.1.0.dist-info/WHEEL
keyrunes_python_sdk-0.1.0.dist-info/RECORD
