Metadata-Version: 2.3
Name: keyrunes-python-sdk
Version: 0.1.0
Summary: Python SDK for Keyrunes Authorization System
License: AGPL
Keywords: keyrunes,authorization,rbac,abac,security,authentication,permissions
Author: keyrunes
Author-email: contact@singularjourney.host
Maintainer: jonatasoli
Maintainer-email: contact@jonatasoli.dev
Requires-Python: >=3.10.1,<4.0
Classifier: Development Status :: 3 - Alpha
Classifier: Intended Audience :: Developers
Classifier: License :: OSI Approved :: MIT License
Classifier: License :: Other/Proprietary License
Classifier: Programming Language :: Python :: 3
Classifier: Programming Language :: Python :: 3.11
Classifier: Programming Language :: Python :: 3.12
Classifier: Programming Language :: Python :: 3.13
Classifier: Programming Language :: Python :: 3.10
Classifier: Programming Language :: Python :: 3.14
Classifier: Topic :: Security
Classifier: Topic :: Software Development :: Libraries :: Python Modules
Classifier: Topic :: System :: Systems Administration :: Authentication/Directory
Requires-Dist: httpx (>=0.28.1,<0.29.0)
Requires-Dist: pydantic[email] (>=2.0.0,<3.0.0)
Requires-Dist: pyjwt (>=2.9.0,<3.0.0)
Project-URL: Documentation, https://github.com/jonatasoli/keyrunes-python-sdk#readme
Project-URL: Homepage, https://keyrunes.com
Project-URL: Repository, https://github.com/jonatasoli/keyrunes-python-sdk
